docs/api.rst
docs/conf.py
docs/index.rst
docs/make.bat
docs/requirements.txt
docs/usage.rst
docs/_build/genindex.html
docs/_build/index.html
docs/_build/search.html
docs/_build/searchindex.js
docs/_build/usage.html
docs/_build/_modules/index.html
docs/_build/_modules/ytubeinsight/analyzer.html
docs/_build/_modules/ytubeinsight/exceptions.html
docs/_build/_sources/index.rst.txt
docs/_build/_sources/usage.rst.txt
docs/_build/_static/_sphinx_javascript_frameworks_compat.js
docs/_build/_static/basic.css
docs/_build/_static/doctools.js
docs/_build/_static/documentation_options.js
docs/_build/_static/jquery.js
docs/_build/_static/language_data.js
docs/_build/_static/pygments.css
docs/_build/_static/searchtools.js
docs/_build/_static/sphinx_highlight.js
docs/_build/_static/css/badge_only.css
docs/_build/_static/css/theme.css
docs/_build/_static/js/badge_only.js
docs/_build/_static/js/html5shiv-printshiv.min.js
docs/_build/_static/js/html5shiv.min.js
docs/_build/_static/js/theme.js
ytubeinsight/__init__.py
ytubeinsight/analyzer.py
ytubeinsight/exceptions.py
ytubeinsight/utils.py
ytubeinsight-0.1.2.dist-info/LICENSE
ytubeinsight-0.1.2.dist-info/METADATA
ytubeinsight-0.1.2.dist-info/WHEEL
ytubeinsight-0.1.2.dist-info/entry_points.txt
ytubeinsight-0.1.2.dist-info/top_level.txt
ytubeinsight-0.1.2.dist-info/RECORD
