Metadata-Version: 2.1
Name: ytubeinsight
Version: 0.1.2
Summary: A Python package for YouTube channel analytics
Author-email: "Md. Fahim Bin Amin" <fahimbinamin@gmail.com>
License: MIT License
Project-URL: Homepage, https://github.com/FahimFBA/ytubeinsight
Project-URL: Bug Reports, https://github.com/FahimFBA/ytubeinsight/issues
Project-URL: Source, https://github.com/FahimFBA/ytubeinsight
Project-URL: Documentation, https://ytubeinsight.readthedocs.io/
Keywords: youtube,analytics,api
Classifier: Development Status :: 3 - Alpha
Classifier: Intended Audience :: Developers
Classifier: License :: OSI Approved :: MIT License
Classifier: Operating System :: OS Independent
Classifier: Programming Language :: Python :: 3
Classifier: Programming Language :: Python :: 3.6
Classifier: Programming Language :: Python :: 3.7
Classifier: Programming Language :: Python :: 3.8
Classifier: Programming Language :: Python :: 3.9
Classifier: Programming Language :: Python :: 3.10
Requires-Python: >=3.6
License-File: LICENSE
Requires-Dist: google-api-python-client>=2.0.0
Requires-Dist: requests>=2.25.0
Requires-Dist: beautifulsoup4>=4.9.0
Provides-Extra: dev
Requires-Dist: pytest>=6.0; extra == "dev"
Requires-Dist: pytest-cov>=2.0; extra == "dev"
Requires-Dist: flake8>=3.9; extra == "dev"
Requires-Dist: black>=21.0; extra == "dev"
Requires-Dist: isort>=5.0; extra == "dev"
Provides-Extra: docs
Requires-Dist: sphinx>=3.0; extra == "docs"
Requires-Dist: sphinx-rtd-theme>=0.5; extra == "docs"
